smart_reading/.DS_Store
smart_reading/__init__.py
smart_reading/book.py
smart_reading/stats.py
smart_reading/samples/Benn_Ch_II_The_Metaphysicians.txt
smart_reading/samples/Galileo_The_Sidereal_Messenger.epub
smart_reading/samples/PhysRev.47.777.pdf
smart_reading-1.1.6.dist-info/METADATA
smart_reading-1.1.6.dist-info/RECORD
smart_reading-1.1.6.dist-info/WHEEL
smart_reading-1.1.6.dist-info/top_level.txt
