Metadata-Version: 2.1
Name: smart-reading
Version: 1.1.6
Summary: An NLTK-based toolkit aimed at increasing the understanding of various texts.
Home-page: https://github.com/andredelft/smart_reading
Author: Andre van Delft
Author-email: andrevandelft@outlook.com
License: UNKNOWN
Keywords: ebook understanding nltk reading toolkit
Platform: UNKNOWN
Classifier: Development Status :: 4 - Beta
Classifier: Programming Language :: Python :: 2.7
Classifier: Programming Language :: Python :: 3
Requires-Python: >=2.7
Requires-Dist: nltk
Requires-Dist: networkx
Requires-Dist: numpy
Requires-Dist: matplotlib
